agp/__init__.py
agp/agptools.py
agp/assemble.py
agp/bed.py
agp/fasta.py
agp/flip.py
agp/join.py
agp/remove.py
agp/rename.py
agp/sanitize.py
agp/split.py
agp/transform.py
bio_agptools-0.0.3.dist-info/licenses/LICENSE
bio_agptools-0.0.3.dist-info/METADATA
bio_agptools-0.0.3.dist-info/WHEEL
bio_agptools-0.0.3.dist-info/entry_points.txt
bio_agptools-0.0.3.dist-info/top_level.txt
bio_agptools-0.0.3.dist-info/RECORD
