Metadata-Version: 2.4
Name: bio_agptools
Version: 0.0.3
Summary: Tools for working with agp files
Author-email: "Edward S. Ricemeyer" <edward.ricemeyer@gmail.com>
License-Expression: MIT
Project-URL: Homepage, https://github.com/WarrenLab/agptools
Project-URL: Issues, https://github.com/WarrenLab/agptools/issues
Classifier: Programming Language :: Python :: 3
Classifier: Operating System :: OS Independent
Requires-Python: >=3.7
License-File: LICENSE
Requires-Dist: screed
Requires-Dist: pyfaidx
Provides-Extra: dev
Requires-Dist: bumpver; extra == "dev"
Requires-Dist: pip-tools; extra == "dev"
Requires-Dist: mypy; extra == "dev"
Requires-Dist: ruff; extra == "dev"
Provides-Extra: test
Requires-Dist: pytest; extra == "test"
Requires-Dist: pytest-cov; extra == "test"
Requires-Dist: pytest-html; extra == "test"
Requires-Dist: genbadge[all]; extra == "test"
Requires-Dist: mypy; extra == "test"
Requires-Dist: ruff; extra == "test"
Provides-Extra: docs
Requires-Dist: mkdocs; extra == "docs"
Requires-Dist: mkdocs-material; extra == "docs"
Requires-Dist: mkdocstrings; extra == "docs"
Requires-Dist: mkdocstrings-python; extra == "docs"
Requires-Dist: pygments; extra == "docs"
Dynamic: license-file
